domain_admin/__init__.py
domain_admin/compat.py
domain_admin/log.py
domain_admin/main.py
domain_admin/version.py
domain_admin/api/__init__.py
domain_admin/api/address_api.py
domain_admin/api/auth_api.py
domain_admin/api/cert_api.py
domain_admin/api/certificate_api.py
domain_admin/api/check_wechat_api.py
domain_admin/api/deploy_cert_api.py
domain_admin/api/dns_api.py
domain_admin/api/domain_api.py
domain_admin/api/domain_info_api.py
domain_admin/api/group_api.py
domain_admin/api/group_user_api.py
domain_admin/api/host_api.py
domain_admin/api/ip_api.py
domain_admin/api/issue_certificate_api.py
domain_admin/api/log_async_task_api.py
domain_admin/api/log_monitor_api.py
domain_admin/api/log_operation_api.py
domain_admin/api/log_scheduler_api.py
domain_admin/api/monitor_api.py
domain_admin/api/notify_api.py
domain_admin/api/prometheus_api.py
domain_admin/api/system_api.py
domain_admin/api/tag_api.py
domain_admin/api/user_api.py
domain_admin/api/whois_api.py
domain_admin/config/__init__.py
domain_admin/config/default_config.py
domain_admin/config/env_config.py
domain_admin/config/runtime_config.py
domain_admin/enums/__init__.py
domain_admin/enums/challenge_deploy_type_enum.py
domain_admin/enums/config_key_enum.py
domain_admin/enums/deploy_status_enum.py
domain_admin/enums/dns_type_enum.py
domain_admin/enums/event_enum.py
domain_admin/enums/host_auth_type_enum.py
domain_admin/enums/monitor_status_enum.py
domain_admin/enums/monitor_type_enum.py
domain_admin/enums/notify_type_enum.py
domain_admin/enums/object_enum.py
domain_admin/enums/operation_enum.py
domain_admin/enums/role_enum.py
domain_admin/enums/source_enum.py
domain_admin/enums/ssl_deploy_type_enum.py
domain_admin/enums/ssl_type_enum.py
domain_admin/enums/status_enum.py
domain_admin/enums/time_unit_enum.py
domain_admin/enums/valid_status_enum.py
domain_admin/enums/version_enum.py
domain_admin/i18n/__init__.py
domain_admin/i18n/config.py
domain_admin/i18n/main.py
domain_admin/migrate/__init__.py
domain_admin-1.6.74.dist-info/licenses/LICENSE
domain_admin-1.6.74.dist-info/METADATA
domain_admin-1.6.74.dist-info/WHEEL
domain_admin-1.6.74.dist-info/top_level.txt
domain_admin-1.6.74.dist-info/zip-safe
domain_admin-1.6.74.dist-info/RECORD
