Metadata-Version: 2.4
Name: domain-admin
Version: 1.6.74
Summary: a domain ssl cert admin
Home-page: https://github.com/dromara/domain-admin
Author: Peng Shiyu
Author-email: pengshiyuyx@gmail.com
License: MIT
Keywords: domain,ssl,cert,web,monitor
Platform: any
Classifier: Development Status :: 5 - Production/Stable
Classifier: Intended Audience :: Developers
Classifier: License :: OSI Approved :: MIT License
Classifier: Operating System :: OS Independent
Classifier: Programming Language :: Python
Classifier: Programming Language :: Python :: 2
Classifier: Programming Language :: Python :: 2.7
Classifier: Programming Language :: Python :: 3
Classifier: Programming Language :: Python :: 3.4
Classifier: Programming Language :: Python :: 3.5
Classifier: Programming Language :: Python :: 3.6
Classifier: Programming Language :: Python :: 3.7
Classifier: Programming Language :: Python :: 3.8
Classifier: Programming Language :: Python :: 3.9
Classifier: Programming Language :: Python :: 3.10
Classifier: Programming Language :: Python :: 3.11
Classifier: Programming Language :: Python :: 3.12
Classifier: Topic :: Internet :: WWW/HTTP :: Dynamic Content
Classifier: Topic :: Internet :: WWW/HTTP :: WSGI :: Application
Classifier: Topic :: Software Development :: Libraries :: Application Frameworks
Classifier: Topic :: Software Development :: Libraries :: Python Modules
License-File: LICENSE
Requires-Dist: six
Requires-Dist: Flask
Requires-Dist: peewee
Requires-Dist: werkzeug
Requires-Dist: Jinja2
Requires-Dist: requests
Requires-Dist: pymysql
Requires-Dist: Flask-Cors
Requires-Dist: python-dateutil
Requires-Dist: apscheduler
Requires-Dist: PyJWT
Requires-Dist: bcrypt
Requires-Dist: tldextract
Requires-Dist: python-dotenv
Requires-Dist: environs
Requires-Dist: pyOpenSSL
Requires-Dist: prometheus-client
Requires-Dist: acme
Requires-Dist: fabric
Requires-Dist: dnspython
Requires-Dist: openpyxl
Requires-Dist: aliyun-python-sdk-alidns
Requires-Dist: tencentcloud-sdk-python
Requires-Dist: alibabacloud_cdn20180510==4.0.0
Requires-Dist: alibabacloud_cas20200407==1.4.0
Requires-Dist: alibabacloud_dcdn20180115==2.4.0
Requires-Dist: oss2
Requires-Dist: diskcache
Dynamic: author
Dynamic: author-email
Dynamic: classifier
Dynamic: description
Dynamic: description-content-type
Dynamic: home-page
Dynamic: keywords
Dynamic: license
Dynamic: license-file
Dynamic: platform
Dynamic: requires-dist
Dynamic: summary
